spi.py
python3_spi-0.3.1.dist-info/LICENSE
python3_spi-0.3.1.dist-info/METADATA
python3_spi-0.3.1.dist-info/WHEEL
python3_spi-0.3.1.dist-info/top_level.txt
python3_spi-0.3.1.dist-info/RECORD
