Metadata-Version: 2.1
Name: python3-spi
Version: 0.3.1
Summary: Python interface for SPI communications
Home-page: https://github.com/tkegan/python-spi
Author: Tom Stokes, Tom Egan
Author-email: tom@tomegan.tech
License: MIT
Platform: UNKNOWN
Classifier: Development Status :: 5 - Production/Stable
Classifier: Intended Audience :: Developers
Classifier: Operating System :: POSIX :: Linux
Classifier: Topic :: Software Development :: Embedded Systems
Classifier: License :: OSI Approved :: MIT License
Classifier: Programming Language :: Python :: 2.7
Classifier: Programming Language :: Python :: 3
Requires-Python: >=2.7, !=3.0.*, <4
